{
  "main": {
    "id": "9471948429c23cc4",
    "type": "split",
    "children": [
      {
        "id": "9f95d774e1e63c9d",
        "type": "tabs",
        "children": [
          {
            "id": "24f3d5aff179f263",
            "type": "leaf",
            "state": {
              "type": "markdown",
              "state": {
                "file": "Люди/Виктория Григорьева.md",
                "mode": "source",
                "source": false
              }
            }
          },
          {
            "id": "3b865876cee0f54e",
            "type": "leaf",
            "state": {
              "type": "graph",
              "state": {}
            }
          }
        ],
        "currentTab": 1
      }
    ],
    "direction": "vertical"
  },
  "left": {
    "id": "7efde2ef4410d361",
    "type": "split",
    "children": [
      {
        "id": "0381f93038258607",
        "type": "tabs",
        "children": [
          {
            "id": "5264bfce54c1d421",
            "type": "leaf",
            "state": {
              "type": "file-explorer",
              "state": {
                "sortOrder": "alphabetical"
              }
            }
          },
          {
            "id": "c2a4287c7eb95fd2",
            "type": "leaf",
            "state": {
              "type": "search",
              "state": {
                "query": "tag:#газлайтинг  ",
                "matchingCase": false,
                "explainSearch": false,
                "collapseAll": false,
                "extraContext": false,
                "sortOrder": "alphabetical"
              }
            }
          },
          {
            "id": "3701d92111c07409",
            "type": "leaf",
            "state": {
              "type": "bookmarks",
              "state": {}
            }
          }
        ]
      }
    ],
    "direction": "horizontal",
    "width": 300
  },
  "right": {
    "id": "0363ce5bb355b2c7",
    "type": "split",
    "children": [
      {
        "id": "4a56db465b4f7486",
        "type": "tabs",
        "children": [
          {
            "id": "f250d89abf56048a",
            "type": "leaf",
            "state": {
              "type": "backlink",
              "state": {
                "collapseAll": false,
                "extraContext": false,
                "sortOrder": "alphabetical",
                "showSearch": false,
                "searchQuery": "",
                "backlinkCollapsed": false,
                "unlinkedCollapsed": true
              }
            }
          },
          {
            "id": "8fb121252377080e",
            "type": "leaf",
            "state": {
              "type": "outgoing-link",
              "state": {
                "linksCollapsed": false,
                "unlinkedCollapsed": true
              }
            }
          },
          {
            "id": "b395a69520cb3146",
            "type": "leaf",
            "state": {
              "type": "tag",
              "state": {
                "sortOrder": "frequency",
                "useHierarchy": true
              }
            }
          },
          {
            "id": "862c8d92c493fc51",
            "type": "leaf",
            "state": {
              "type": "outline",
              "state": {}
            }
          }
        ]
      }
    ],
    "direction": "horizontal",
    "width": 300
  },
  "left-ribbon": {
    "hiddenItems": {
      "switcher:Меню быстрого перехода": false,
      "graph:Граф": false,
      "canvas:Создать новый холст": false,
      "daily-notes:Сегодняшняя заметка": false,
      "templates:Вставить шаблон": false,
      "command-palette:Открыть палитру команд": false,
      "obsidian-excalidraw-plugin:Create new drawing": false
    }
  },
  "active": "3b865876cee0f54e",
  "lastOpenFiles": [
    "Люди/Виктория Григорьева.md",
    "Люди/Эдуард Чагиров.md",
    "Люди/Рицка (Александр Барышников).md",
    "Люди/Андрей Гончаров.md",
    "Мысли/27.06.2024.md",
    "Люди/Дарья Цапина.md",
    "Люди/Вероника Гончарова (Крючкова).md",
    "Люди/Вадим Севериков.md",
    "Люди/Антон Ридель.md",
    "Люди/Дмитрий Цапин.md",
    "имиджборд.md",
    "Люди",
    "Микробложек/ИПР 06.24 - 03.25.md",
    "Микробложек/Выводы после срачей.md",
    "Микробложек/Встроенный в Node.JS тест-раннер.md",
    "Микробложек/useStore в бигтехе.md",
    "Выводы после срачей",
    "Микровики/Видео игры/Minecraft.md",
    "Микровики/Obsidian.md",
    "Микровики/Программирование/Язык программирования.md",
    "Микровики/Программирование/Языки разметки/Язык разметки.md",
    "Микровики/Программирование/Языки разметки/Markdown.md",
    "Микровики/Программирование/Языки разметки",
    "Микровики/Нетсталкинг.md",
    "Микровики/Видео игры/Видео игры.md",
    "Микровики/Видео игры/Beam.NG.md",
    "Микровики/Видео игры/Euro Truck Simulator.md",
    "Микровики/Видео игры/Factorio.md",
    "Видосы/Про тулзы.md",
    "Микровики/Видео игры",
    "Микробложек/assets/Pasted image 20240627202523.png",
    "Микробложек/assets",
    "Микробложек/assets/Pasted image 20240627202652.png",
    "Микробложек/assets/Pasted image 20240627202631.png",
    "Микробложек",
    "Микровики/Программирование",
    "Видосы/Про игры",
    "Мысли",
    "Микровики/Программирование/Алгоритмы",
    "532d3659db86ed0d86fcc57ef38acc45.avif",
    "Без названия 1.canvas",
    "Без названия.canvas"
  ]
}